src/fadd/fadd.v
module fadd
(
    input [31:0] a,
    input [31:0] b,
    output reg[31:0] out
);

// setup a
wire sign_a = a[31];
wire [7:0] exponent_a = a[30:23];
wire [24:0] fraction_a = |exponent_a ? {2'b01, a[22:0]} : 25'b0; 

// setup b
wire sign_b = b[31];
wire [7:0] exponent_b = b[30:23];
wire [24:0] fraction_b = |exponent_b ? {2'b01, b[22:0]} : 25'b0;

// small alu
wire [7:0] exponent_diff = exponent_a - exponent_b;

// select signal mux
wire select = a[30:0] < b[30:0];

wire [7:0] exponent_diff_abs = exponent_diff[7] ? -exponent_diff : exponent_diff;

// fraction muxes
wire [48:0] fraction_larger = {select ? fraction_b : fraction_a, 24'b0};
wire [48:0] fraction_tmp = {select ? fraction_a : fraction_b, 24'b0};

// fraction shift right
wire [48:0] fraction_smaller = fraction_tmp >> exponent_diff_abs;

// sign muxes
wire sign_larger = select ? sign_b : sign_a;

// big alu
wire [48:0] fraction_prenorm = sign_a ^ sign_b ? fraction_larger - fraction_smaller : fraction_larger + fraction_smaller;

// exponent mux
wire [7:0] exponent_larger = select ? exponent_b : exponent_a;

// normalise block
integer index;
reg [48:0] fraction_postnorm;
reg [7:0] exponent_postnorm;

always @(*) begin

    fraction_postnorm = fraction_prenorm;
    exponent_postnorm = exponent_larger;
    if (sign_a ^ sign_b) begin
        for (index = 22; index >= 0; index--) begin
            if (fraction_postnorm[47] == 0) begin
                fraction_postnorm = fraction_postnorm << 1;
                exponent_postnorm = exponent_postnorm - 1;
            end
        end
    end else begin
        if (fraction_prenorm[48]) begin
            fraction_postnorm = fraction_prenorm >> 1;
            exponent_postnorm = exponent_larger + 1;
        end else begin
            fraction_postnorm = fraction_prenorm;
            exponent_postnorm = exponent_larger;
        end
    end

    out = {sign_larger, exponent_postnorm, fraction_postnorm[46:24]};
end

endmodule

src/fadd/tb_fadd.v
`timescale 1ps/1ps

`include "fadd.v"

module fadd_tb;

reg [31:0] a, b;
wire [31:0] out;

reg clk = 1'b1;

fadd uut(a, b, out);

always clk = #5 ~clk;

initial begin

	$dumpfile("fadd_out.vcd");
	$dumpvars(0, fadd_tb);

    test_case(32'h4A36_00CA, 32'hC93C_97A8, 32'h4A06_DAE0);
    test_case(32'h498A_D804, 32'hCA1E_F022, 32'hC9B3_0840);
    test_case(32'h4AA4_6873, 32'h49CD_A038, 32'h4AD7_D081);
    test_case(32'hC9D5_32B0, 32'h490C_91C1, 32'hC98E_E9D0);
    test_case(32'hC8DE_2B1B, 32'h4A47_E514, 32'h4A2C_1FB1);
    test_case(32'h4A74_30F1, 32'h499E_2E20, 32'h4AA1_A400);
    test_case(32'h4991_E4C7, 32'h4A03_8953, 32'h4A4C_7BB6);
    test_case(32'h4A16_B076, 32'hC8C6_08CB, 32'h49FB_DEB9);
    test_case(32'h4921_7B24, 32'h494E_793B, 32'h49B7_FA30);
    test_case(32'hCA86_532E, 32'h4982_FD22, 32'hCA4B_27CB);
    test_case(32'hC871_BDAC, 32'hC9B4_82ED, 32'hC9D2_BAA2);
    test_case(32'h4A9C_31FF, 32'h49DC_F026, 32'h4AD3_6E08);
    test_case(32'h47A7_5C74, 32'hC967_24C7, 32'hC952_3938);
    test_case(32'h4834_A468, 32'hC93D_0936, 32'hC90F_E01C);
    test_case(32'h4AEF_BD8E, 32'h4972_5577, 32'h4B07_041E);
    test_case(32'hC819_3965, 32'hC9A5_6F44, 32'hC9B8_9671);
    test_case(32'hC96A_3E8C, 32'h496E_F9C6, 32'h4697_6740);
    test_case(32'hC7BC_4D05, 32'h4982_8A0C, 32'h496D_8A77);
    test_case(32'hCA80_26F8, 32'h49B4_7882, 32'hCA26_11AF);
    test_case(32'h4AB5_C0E5, 32'h4AA1_2D57, 32'h4B2B_771E);
    test_case(32'hCAA5_DDEA, 32'h4984_621D, 32'hCA84_C563);
    test_case(32'hC9DA_07B3, 32'h4A05_7FD0, 32'h48C3_DFB4);
    test_case(32'h49C2_02F6, 32'h49C4_9B90, 32'h4A43_4F43);
    test_case(32'hC8E2_6BEA, 32'h4A4C_E5B7, 32'h4A30_983A);
    test_case(32'hCA64_030C, 32'h4AA2_4E26, 32'h49C1_3280);
    test_case(32'h4894_B8F8, 32'hC7FB_5EF5, 32'h482B_C276);
    test_case(32'hCAA7_3301, 32'hC925_4A8D, 32'hCABB_DC53);
    test_case(32'hC95E_8874, 32'hCA40_94B7, 32'hCA78_36D4);
    test_case(32'h4834_E5CE, 32'hCA98_BCB5, 32'hCA93_1587);
    test_case(32'hCA80_0F7F, 32'hC8BE_4DA7, 32'hCA8B_F459);
    test_case(32'hC8F1_5AEC, 32'h48B4_410E, 32'hC7F4_6778);
    test_case(32'h4A51_FA3C, 32'h4984_6E87, 32'h4A8A_18C0);
    test_case(32'h49CB_9780, 32'hC902_35B3, 32'h498A_7CA6);
    test_case(32'hCA28_C481, 32'hC98E_2183, 32'hCA6F_D542);
    test_case(32'h48F7_6BAC, 32'h49C6_F509, 32'h4A02_67FA);
    test_case(32'h4A88_09BA, 32'h49B6_D025, 32'h4AB5_BDC3);
    test_case(32'hC911_2D58, 32'h4A27_97C8, 32'h4A03_4C72);
    test_case(32'h4715_BF67, 32'h498B_4657, 32'h498F_F452);
    test_case(32'hCAB8_5186, 32'h499D_945E, 32'hCA90_EC6E);
    test_case(32'h4A4A_0537, 32'hCAD6_9663, 32'hCA63_278F);
    test_case(32'hC6AA_51EF, 32'hC9ED_E0EC, 32'hC9F0_8A34);
    test_case(32'h496C_25A9, 32'hCA8D_299A, 32'hCA5F_49CA);
    test_case(32'h4841_04FF, 32'hC910_46A7, 32'hC8C0_0ACE);
    test_case(32'h4AE5_B6B4, 32'hCA15_27FF, 32'h4A9B_22B4);
    test_case(32'hCA9A_68CA, 32'h4989_3EA4, 32'hCA70_3242);
    test_case(32'h463F_D1E1, 32'h4904_179B, 32'h4907_16E3);
    test_case(32'h4A13_673A, 32'h486E_B87C, 32'h4A22_52C2);
    test_case(32'hCA0F_7140, 32'h4863_1EB8, 32'hCA01_3F54);
    test_case(32'hC92E_1F26, 32'h4A82_43DB, 32'h4A58_FFEC);
    test_case(32'hCA39_75F3, 32'hC9C7_7708, 32'hCA8E_98BC);
    $finish;
end

task test_case(
    input [31:0] a_in,
    input [31:0] b_in,
    input [31:0] expected_out
); begin
    @(negedge clk) begin
        a = a_in;
        b = b_in;
    end
    @(posedge clk) begin
        if (expected_out == out)
            $display("Success: %h + %h = %h", a_in, b_in, out);
        else
            $display("Error:   %h + %h = %h | %h", a_in, b_in, out, expected_out);
    end
end
endtask

endmodule

src/fadd/fadd_out.vcd
$date
	Sun May  9 02:15:57 2021
$end
$version
	Icarus Verilog
$end
$timescale
	1ps
$end
$scope module fadd_tb $end
$var wire 32 ! out [31:0] $end
$var reg 32 " a [31:0] $end
$var reg 32 # b [31:0] $end
$var reg 1 $ clk $end
$scope module uut $end
$var wire 32 % a [31:0] $end
$var wire 32 & b [31:0] $end
$var wire 1 ' sign_larger $end
$var wire 1 ( sign_b $end
$var wire 1 ) sign_a $end
$var wire 1 * select $end
$var wire 49 + fraction_tmp [48:0] $end
$var wire 49 , fraction_smaller [48:0] $end
$var wire 49 - fraction_prenorm [48:0] $end
$var wire 49 . fraction_larger [48:0] $end
$var wire 25 / fraction_b [24:0] $end
$var wire 25 0 fraction_a [24:0] $end
$var wire 8 1 exponent_larger [7:0] $end
$var wire 8 2 exponent_diff_abs [7:0] $end
$var wire 8 3 exponent_diff [7:0] $end
$var wire 8 4 exponent_b [7:0] $end
$var wire 8 5 exponent_a [7:0] $end
$var reg 8 6 exponent_postnorm [7:0] $end
$var reg 49 7 fraction_postnorm [48:0] $end
$var reg 32 8 out [31:0] $end
$var integer 32 9 index [31:0] $end
$upscope $end
$scope task test_case $end
$var reg 32 : a_in [31:0] $end
$var reg 32 ; b_in [31:0] $end
$upscope $end
$upscope $end
$enddefinitions $end
#0
$dumpvars
b1011111000011010111101101101101 ;
b11100000010001100001101111101100 :
bx 9
bx 8
bx 7
bx 6
bx 5
bx 4
bx 3
bx 2
bx 1
b0xxxxxxxxxxxxxxxxxxxxxxxx 0
b0xxxxxxxxxxxxxxxxxxxxxxxx /
b0xxxxxxxxxxxxxxxxxxxxxxxx000000000000000000000000 .
bx -
bx ,
b0xxxxxxxxxxxxxxxxxxxxxxxx000000000000000000000000 +
x*
x)
x(
x'
bx &
bx %
1$
bx #
bx "
bx !
$end
#5
b101000101011110100010000110000000000000000000000 7
b101000101011110100010000110000000000000000000000 -
b1000110101111011011011010000000000000000000000 ,
b100011010111101101101101000000000000000000000000 +
b10 2
b100011010111101101101101 /
b110001100001101111101100000000000000000000000000 .
1'
b11100000001000101011110100010000 !
b11100000001000101011110100010000 8
b11111111111111111111111111111111 9
b11000000 6
b11000000 1
b110001100001101111101100 0
0(
b10 3
b10111110 4
0*
1)
b11000000 5
b1011111000011010111101101101101 #
b1011111000011010111101101101101 &
b11100000010001100001101111101100 "
b11100000010001100001101111101100 %
0$
#10
b11011111010011000110000101111110 ;
b1011110101001111111101011010001 :
1$
#15
b111100001100100000101011000000000000000000000000 7
b11110000110010000010101100000000000000000000000 -
b110011000110000101111110 /
b11011110111100001100100000101011 !
b11011110111100001100100000101011 8
b11111111111111111111111111111111 9
b10111101 6
b1 2
b101001111111101011010001 0
b110011000110000101111110000000000000000000000000 .
b10100111111110101101000100000000000000000000000 ,
b101001111111101011010001000000000000000000000000 +
b10111110 1
1(
0)
b11111111 3
b10111101 5
1*
b11011111010011000110000101111110 #
b11011111010011000110000101111110 &
b1011110101001111111101011010001 "
b1011110101001111111101011010001 %
0$
#20
b1011111101111111011110100010110 ;
b11011111101101101011100111010010 :
1$
#25
b101111111011110100010110000000000000000000000000 .
b10010000001101000100000000000000000000000000 -
b101101101011100111010010000000000000000000000000 +
b101111111011110100010110 /
b1011101100100000011010001000000 !
b1011101100100000011010001000000 8
b11111111111111111111111111111111 9
b10111011 6
b100100000011010001000000000000000000000000000000 7
b101101101011100111010010000000000000000000000000 ,
b0 2
b101101101011100111010010 0
0'
b10111111 1
0(
b10111111 4
1)
b0 3
b10111111 5
1*
b1011111101111111011110100010110 #
b1011111101111111011110100010110 &
b11011111101101101011100111010010 "
b11011111101101101011100111010010 %
0$
#30
b11011110101100010100111011011110 ;
b11011111001110111000110110110011 :
1$
#35
b1000101000011010100100010000000000000000000000000 -
b11011111100010100001101010010001 !
b11011111100010100001101010010001 8
b10111111 6
b100010100001101010010001000000000000000000000000 7
b101100010100111011011110 /
b101110111000110110110011000000000000000000000000 .
b101100010100111011011110000000000000000000000000 +
1'
b10111110 1
b10110001010011101101111000000000000000000000000 ,
b1 2
b101110111000110110110011 0
1(
b10111101 4
0*
b1 3
b10111110 5
b11011110101100010100111011011110 #
b11011110101100010100111011011110 &
b11011111001110111000110110110011 "
b11011111001110111000110110110011 %
0$
#40
b11011110110011101111010000101010 ;
b11011111111001101101110100010101 :
1$
#45
b110011101111010000101010000000000000000000000000 +
b1000110101001101000011111100000000000000000000000 -
b11100000000011010100110100001111 !
b11100000000011010100110100001111 8
b11000000 6
b100011010100110100001111110000000000000000000000 7
b111001101101110100010101000000000000000000000000 .
b110011101111010000101010 /
b1100111011110100001010100000000000000000000000 ,
b10 2
b10111111 1
b111001101101110100010101 0
b10 3
b10111111 5
b11011110110011101111010000101010 #
b11011110110011101111010000101010 &
b11011111111001101101110100010101 "
b11011111111001101101110100010101 %
0$
#50
b11011111011101000101110011111110 ;
b1011111000100110010001111011010 :
1$
#55
b11000010011100100100100000000000000000000000000 -
b111101000101110011111110 /
b111101000101110011111110000000000000000000000000 .
b100100110010001111011010000000000000000000000000 +
b11011110110000100111001001001000 !
b11011110110000100111001001001000 8
b11111111111111111111111111111111 9
b10111101 6
b110000100111001001001000000000000000000000000000 7
b100100110010001111011010000000000000000000000000 ,
b0 2
b10111110 1
b100100110010001111011010 0
b10111110 4
1*
0)
b0 3
b10111110 5
b11011111011101000101110011111110 #
b11011111011101000101110011111110 &
b1011111000100110010001111011010 "
b1011111000100110010001111011010 %
0$
#60
b11011110111001011110000001110101 ;
b1011111011101110101110111110111 :
1$
#65
b100001000110110110111100100000000000000000000000 -
b1011111000001000110110110111100 !
b1011111000001000110110110111100 8
b11111111111111111111111111111111 9
b10111110 6
b100001000110110110111100100000000000000000000000 7
b1 2
b111001011110000001110101 /
b111101110101110111110111 0
b111101110101110111110111000000000000000000000000 .
b11100101111000000111010100000000000000000000000 ,
b111001011110000001110101000000000000000000000000 +
0'
b1 3
b10111101 4
0*
b11011110111001011110000001110101 #
b11011110111001011110000001110101 &
b1011111011101110101110111110111 "
b1011111011101110101110111110111 %
0$
#70
b1100000010111101100101100000001 ;
b1100000011100001100110001110001 :
1$
#75
b111001111100101110111001000000000000000000000000 7
b110111101100101100000001000000000000000000000000 +
b1110011111001011101110010000000000000000000000000 -
b111100001100110001110001000000000000000000000000 .
b1100000111001111100101110111001 !
b1100000111001111100101110111001 8
b11000001 6
b110111101100101100000001 /
b110111101100101100000001000000000000000000000000 ,
b0 2
b11000000 1
b111100001100110001110001 0
0(
b11000000 4
b0 3
b11000000 5
b1100000010111101100101100000001 #
b1100000010111101100101100000001 &
b1100000011100001100110001110001 "
b1100000011100001100110001110001 %
0$
#80
b1100000001010100110011011000100 ;
b11011111001111110110000001111111 :
1$
#85
b11110101000111010100100010000000000000000000000 -
b101010100110011011000100 /
b1011111111101010001110101001000 !
b1011111111101010001110101001000 8
b11111111111111111111111111111111 9
b10111111 6
b111101010001110101001000100000000000000000000000 7
b10 2
b101111110110000001111111 0
b101010100110011011000100000000000000000000000000 .
b1011111101100000011111110000000000000000000000 ,
b101111110110000001111111000000000000000000000000 +
1)
b11111110 3
b10111110 5
1*
b1100000001010100110011011000100 #
b1100000001010100110011011000100 &
b11011111001111110110000001111111 "
b11011111001111110110000001111111 %
0$
#90
b1100000000100011101001000000000 ;
b11011111011110010001101001001011 :
1$
#95
b1011111101001110001011011011010 !
b1011111101001110001011011011010 8
b11111111111111111111111111111111 9
b10111111 6
b101001110001011011011010100000000000000000000000 7
b10100111000101101101101010000000000000000000000 -
b100100011101001000000000000000000000000000000000 .
b1111100100011010010010110000000000000000000000 ,
b111110010001101001001011000000000000000000000000 +
b100100011101001000000000 /
b111110010001101001001011 0
b1100000000100011101001000000000 #
b1100000000100011101001000000000 &
b11011111011110010001101001001011 "
b11011111011110010001101001001011 %
0$
#100
b11011111100011101010011001001011 ;
b1100000011011111110001101001011 :
1$
#105
b1100000001010001001000000100101 !
b1100000001010001001000000100101 8
b101010001001000000100101100000000000000000000000 -
b100011101010011001001011 /
b11111111111111111111111111111111 9
b11000000 6
b101010001001000000100101100000000000000000000000 7
b1 2
b111011111110001101001011 0
b111011111110001101001011000000000000000000000000 .
b10001110101001100100101100000000000000000000000 ,
b100011101010011001001011000000000000000000000000 +
1(
b10111111 4
0)
b1 3
b11000000 5
0*
b11011111100011101010011001001011 #
b11011111100011101010011001001011 &
b1100000011011111110001101001011 "
b1100000011011111110001101001011 %
0$
#110
b11011111110010010111110101100011 ;
b11100000001111100100110000000101 :
1$
#115
b11001001011111010110001100000000000000000000000 ,
b110010010111110101100011000000000000000000000000 +
b11100000100100011000010101011011 !
b11100000100100011000010101011011 8
b11000001 6
b100100011000010101011011010000000000000000000000 7
b1001000110000101010110110100000000000000000000000 -
b101111100100110000000101000000000000000000000000 .
b110010010111110101100011 /
1'
b101111100100110000000101 0
1)
b11011111110010010111110101100011 #
b11011111110010010111110101100011 &
b11100000001111100100110000000101 "
b11100000001111100100110000000101 %
0$
#120
b11011110111110011101000001110011 ;
b11100000000111111000011101101111 :
1$
#125
b11100000001111101100000101111101 !
b11100000001111101100000101111101 8
b11000000 6
b101111101100000101111101011000000000000000000000 7
b101111101100000101111101011000000000000000000000 -
b111110011101000001110011000000000000000000000000 +
b100111111000011101101111000000000000000000000000 .
b111110011101000001110011000000000000000000000 ,
b11 2
b111110011101000001110011 /
b100111111000011101101111 0
b11 3
b10111101 4
b11011110111110011101000001110011 #
b11011110111110011101000001110011 &
b11100000000111111000011101101111 "
b11100000000111111000011101101111 %
0$
#130
b1100000001011110001010000011011 ;
b1100000011001010111001101110001 :
1$
#135
b11000001 6
b110010100100001111000110000000000000000000000000 7
b1100101001000011110001100000000000000000000000000 -
b101011110001010000011011000000000000000000000000 +
b1100000110010100100001111000110 !
b1100000110010100100001111000110 8
b111001010111001101110001000000000000000000000000 .
b101011110001010000011011000000000000000000000000 ,
b0 2
b101011110001010000011011 /
0'
b111001010111001101110001 0
0(
b0 3
b11000000 4
0)
b1100000001011110001010000011011 #
b1100000001011110001010000011011 &
b1100000011001010111001101110001 "
b1100000011001010111001101110001 %
0$
#140
b1011111011101101101010101100111 ;
b11100000001010101111000110111010 :
1$
#145
b111101101101010101100111000000000000000000000000 +
b11011010011110001100000010000000000000000000000 -
b101010101111000110111010000000000000000000000000 .
b1111011011010101011001110000000000000000000000 ,
b10 2
b111101101101010101100111 /
b11011111110110100111100011000000 !
b11011111110110100111100011000000 8
b11111111111111111111111111111111 9
b10111111 6
b110110100111100011000000100000000000000000000000 7
b101010101111000110111010 0
1'
b10 3
b10111110 4
1)
0*
b1011111011101101101010101100111 #
b1011111011101101101010101100111 &
b11100000001010101111000110111010 "
b11100000001010101111000110111010 %
0$
#150
b11011110111001111010101010110010 ;
b1011111010001001011010001000101 :
1$
#155
b111001111010101010110010000000000000000000000000 +
b10100001101111011101100000000000000000000000000 -
b110001001011010001000101000000000000000000000000 .
b111001111010101010110010 /
b1011110101000011011110111011000 !
b1011110101000011011110111011000 8
b11111111111111111111111111111111 9
b10111101 6
b101000011011110111011000000000000000000000000000 7
b11100111101010101011001000000000000000000000000 ,
b1 2
b110001001011010001000101 0
0'
b10111110 1
1(
b10111101 4
0)
b1 3
b10111110 5
0*
b11011110111001111010101010110010 #
b11011110111001111010101010110010 &
b1011111010001001011010001000101 "
b1011111010001001011010001000101 %
0$
#160
b1011111000101100011011010011011 ;
b11011111100111100100100101101010 :
1$
#165
b10100110010111000011100100000000000000000000000 -
b10010110001101101001101100000000000000000000000 ,
b100101100011011010011011000000000000000000000000 +
b100111100100100101101010000000000000000000000000 .
b100101100011011010011011 /
1'
b11011111001001100101110000111001 !
b11011111001001100101110000111001 8
b11111111111111111111111111111111 9
b10111110 6
b101001100101110000111001000000000000000000000000 7
b10111111 1
b100111100100100101101010 0
0(
b10111110 4
1)
b1 3
b10111111 5
b1011111000101100011011010011011 #
b1011111000101100011011010011011 &
b11011111100111100100100101101010 "
b11011111100111100100100101101010 %
0$
#170
b11100000001111010000001011111010 ;
b11100000011101111110101000001000 :
1$
#175
b101111010000001011111010000000000000000000000000 +
b1101101001110110100000010000000000000000000000000 -
b111101111110101000001000000000000000000000000000 .
b11100000110110100111011010000001 !
b11100000110110100111011010000001 8
b11000001 6
b110110100111011010000001000000000000000000000000 7
b101111010000001011111010 /
b101111010000001011111010000000000000000000000000 ,
b0 2
b11000000 1
b111101111110101000001000 0
1(
b11000000 4
b0 3
b11000000 5
b11100000001111010000001011111010 #
b11100000001111010000001011111010 &
b11100000011101111110101000001000 "
b11100000011101111110101000001000 %
0$
#180
b1011111110010011100000110110100 ;
b11011111110111100011111110101111 :
1$
#185
b101000111110111111011000000000000000000000000 -
b110010011100000110110100000000000000000000000000 ,
b110010011100000110110100000000000000000000000000 +
b110111100011111110101111000000000000000000000000 .
b11011110001000111110111111011000 !
b11011110001000111110111111011000 8
b11111111111111111111111111111111 9
b10111100 6
b101000111110111111011000000000000000000000000000 7
b110010011100000110110100 /
b110111100011111110101111 0
b10111111 1
0(
b10111111 4
b0 3
b10111111 5
0*
b1011111110010011100000110110100 #
b1011111110010011100000110110100 &
b11011111110111100011111110101111 "
b11011111110111100011111110101111 %
0$
#190
b11011110011011011000001001110010 ;
b1100000000001101110111001001001 :
1$
#195
b111011011000001001110010000000000000000000000000 +
b11110000001011000100001111000000000000000000000 -
b100001101110111001001001000000000000000000000000 .
b111011011000001001110010 /
0'
b1011111111100000010110001000011 !
b1011111111100000010110001000011 8
b11111111111111111111111111111111 9
b10111111 6
b111100000010110001000011110000000000000000000000 7
b11101101100000100111001000000000000000000000 ,
b100 2
b11000000 1
b100001101110111001001001 0
1(
b10111100 4
0)
b100 3
b11000000 5
b11011110011011011000001001110010 #
b11011110011011011000001001110010 &
b1100000000001101110111001001001 "
b1100000000001101110111001001001 %
0$
#200
b11100000011010110101001011011011 ;
b1100000010010000111011010101111 :
1$
#205
b1000101101110000101100000000000000000000000000 -
b11011111000010110111000010110000 !
b11011111000010110111000010110000 8
b11111111111111111111111111111111 9
b10111110 6
b100010110111000010110000000000000000000000000000 7
b0 2
b111010110101001011011011 /
b111010110101001011011011000000000000000000000000 .
b110010000111011010101111000000000000000000000000 ,
b110010000111011010101111000000000000000000000000 +
1'
b110010000111011010101111 0
b0 3
b11000000 4
1*
b11100000011010110101001011011011 #
b11100000011010110101001011011011 &
b1100000010010000111011010101111 "
b1100000010010000111011010101111 %
0$
#210
b11011110101100101000011110011001 ;
b1100000011011111000001010000011 :
1$
#215
b110110010011000110001111111000000000000000000000 -
b1100000010110010011000110001111 !
b1100000010110010011000110001111 8
b11111111111111111111111111111111 9
b11000000 6
b110110010011000110001111111000000000000000000000 7
b11 2
b101100101000011110011001 /
b111011111000001010000011 0
b111011111000001010000011000000000000000000000000 .
b101100101000011110011001000000000000000000000 ,
b101100101000011110011001000000000000000000000000 +
0'
b11 3
b10111101 4
0*
b11011110101100101000011110011001 #
b11011110101100101000011110011001 &
b1100000011011111000001010000011 "
b1100000011011111000001010000011 %
0$
#220
b11100000010000110010001101001111 ;
b11011110111100001111100100111010 :
1$
#225
b11100000011000010100001001110110 !
b11100000011000010100001001110110 8
b111000010100001001110110010000000000000000000000 7
b111000010100001001110110010000000000000000000000 -
b110000110010001101001111 /
b110000110010001101001111000000000000000000000000 .
b111100001111100100111010000000000000000000000000 +
1'
b111100001111100100111010000000000000000000000 ,
b11 2
b111100001111100100111010 0
b11000000 4
1*
1)
b11111101 3
b10111101 5
b11100000010000110010001101001111 #
b11100000010000110010001101001111 &
b11011110111100001111100100111010 "
b11011110111100001111100100111010 %
0$
#230
b1100000010111101100111110100011 ;
b11100000011010111000000110010010 :
1$
#235
b11011110010010110001111011110000 !
b11011110010010110001111011110000 8
b10111100 6
b110010110001111011110000000000000000000000000000 7
b11001011000111101111000000000000000000000000 -
b11111111111111111111111111111111 9
b110111101100111110100011 /
b0 2
b111010111000000110010010 0
b111010111000000110010010000000000000000000000000 .
b110111101100111110100011000000000000000000000000 ,
b110111101100111110100011000000000000000000000000 +
0(
b0 3
b11000000 5
0*
b1100000010111101100111110100011 #
b1100000010111101100111110100011 &
b11100000011010111000000110010010 "
b11100000011010111000000110010010 %
0$
#240
b11011110110000110011110010001010 ;
b1100000011100110010000010010100 :
1$
#245
b110110101011100100000010110000000000000000000000 -
b110000110011110010001010000000000000000000000000 +
b1100000010110101011100100000010 !
b1100000010110101011100100000010 8
b111100110010000010010100000000000000000000000000 .
b110000110011110010001010000000000000000000000 ,
b11 2
b110000110011110010001010 /
0'
b11111111111111111111111111111111 9
b11000000 6
b110110101011100100000010110000000000000000000000 7
b111100110010000010010100 0
1(
b11 3
b10111101 4
0)
b11011110110000110011110010001010 #
b11011110110000110011110010001010 &
b1100000011100110010000010010100 "
b1100000011100110010000010010100 %
0$
#250
b1100000010000000011001110111100 ;
b1100000010111100000010010001100 :
1$
#255
b1100000110011110001110000100100 !
b1100000110011110001110000100100 8
b11000001 6
b110011110001110000100100000000000000000000000000 7
b1100111100011100001001000000000000000000000000000 -
b110000000011001110111100000000000000000000000000 +
b110111100000010010001100000000000000000000000000 .
b110000000011001110111100000000000000000000000000 ,
b0 2
b110000000011001110111100 /
b110111100000010010001100 0
0(
b0 3
b11000000 4
b1100000010000000011001110111100 #
b1100000010000000011001110111100 &
b1100000010111100000010010001100 "
b1100000010111100000010010001100 %
0$
#260
b11011111010010011011111010110001 ;
b1100000010111100110111111101011 :
1$
#265
b101011000000000000111110110000000000000000000000 -
b110010011011111010110001000000000000000000000000 +
b110111100110111111101011000000000000000000000000 .
b1100000001011000000000000111110 !
b1100000001011000000000000111110 8
b11111111111111111111111111111111 9
b11000000 6
b101011000000000000111110110000000000000000000000 7
b1100100110111110101100010000000000000000000000 ,
b10 2
b110010011011111010110001 /
b110111100110111111101011 0
1(
b10 3
b10111110 4
b11011111010010011011111010110001 #
b11011111010010011011111010110001 &
b1100000010111100110111111101011 "
b1100000010111100110111111101011 %
0$
#270
b1011101011100101110110111010110 ;
b1100000001000001011101000110100 :
1$
#275
b1100000001001001000010111101011 !
b1100000001001001000010111101011 8
b101001001000010111101011010110000000000000000000 7
b101001001000010111101011010110000000000000000000 -
b111100101110110111010110000000000000000000000000 +
b101000001011101000110100000000000000000000000000 .
b111100101110110111010110000000000000000000 ,
b110 2
b111100101110110111010110 /
b101000001011101000110100 0
0(
b110 3
b10111010 4
b1011101011100101110110111010110 #
b1011101011100101110110111010110 &
b1100000001000001011101000110100 "
b1100000001000001011101000110100 %
0$
#280
b11100000000011001110110100111010 ;
b11100000000111100110101010000111 :
1$
#285
b11000001 6
b100101011010101111100000100000000000000000000000 7
b1001010110101011111000001000000000000000000000000 -
b100011001110110100111010000000000000000000000000 +
b11100000100101011010101111100000 !
b11100000100101011010101111100000 8
b100111100110101010000111000000000000000000000000 .
b100011001110110100111010000000000000000000000000 ,
b0 2
b100011001110110100111010 /
1'
b100111100110101010000111 0
1(
b0 3
b11000000 4
1)
b11100000000011001110110100111010 #
b11100000000011001110110100111010 &
b11100000000111100110101010000111 "
b11100000000111100110101010000111 %
0$
#290
b11100000001001011010110000000111 ;
b1011110100001110010111001100110 :
1$
#295
b100101001100011000111010010000000000000000000000 -
b101001011010110000000111 /
b11100000000101001100011000111010 !
b11100000000101001100011000111010 8
b11111111111111111111111111111111 9
b11000000 6
b100101001100011000111010010000000000000000000000 7
b11 2
b100001110010111001100110 0
b101001011010110000000111000000000000000000000000 .
b100001110010111001100110000000000000000000000 ,
b100001110010111001100110000000000000000000000000 +
0)
b11111101 3
b10111101 5
1*
b11100000001001011010110000000111 #
b11100000001001011010110000000111 &
b1011110100001110010111001100110 "
b1011110100001110010111001100110 %
0$
#300
b1011111101100100010000001101111 ;
b1011111001101111111110001111011 :
1$
#305
b100001110000111101010110010000000000000000000000 7
b101100100010000001101111000000000000000000000000 .
b1000011100001111010101100100000000000000000000000 -
b101101111111110001111011000000000000000000000000 +
0'
b1100000000001110000111101010110 !
b1100000000001110000111101010110 8
b11000000 6
b10111111 1
b101100100010000001101111 /
b10110111111111000111101100000000000000000000000 ,
b1 2
b101101111111110001111011 0
0(
b10111111 4
b11111111 3
b10111110 5
b1011111101100100010000001101111 #
b1011111101100100010000001101111 &
b1011111001101111111110001111011 "
b1011111001101111111110001111011 %
0$
#310
b1100000011101110010110011001101 ;
b1100000000011001111100000010000 :
1$
#315
b111101110010110011001101000000000000000000000000 .
b1100001000010010011011101000000000000000000000000 -
b100011001111100000010000000000000000000000000000 +
b1100000110000100001001001101110 !
b1100000110000100001001001101110 8
b11000001 6
b110000100001001001101110100000000000000000000000 7
b111101110010110011001101 /
b100011001111100000010000000000000000000000000000 ,
b0 2
b100011001111100000010000 0
b11000000 1
b11000000 4
b0 3
b11000000 5
1*
b1100000011101110010110011001101 #
b1100000011101110010110011001101 &
b1100000000011001111100000010000 "
b1100000000011001111100000010000 %
0$
#320
b11100000010100000110101111101000 ;
b1100000010011001000111001011110 :
1$
#325
b111101110110001010000000000000000000000000 -
b110100000110101111101000000000000000000000000000 .
b110011001000111001011110000000000000000000000000 ,
b110011001000111001011110000000000000000000000000 +
1'
b11011101011101110110001010000000 !
b11011101011101110110001010000000 8
b11111111111111111111111111111111 9
b10111010 6
b111101110110001010000000000000000000000000000000 7
b110100000110101111101000 /
b110011001000111001011110 0
1(
b11100000010100000110101111101000 #
b11100000010100000110101111101000 &
b1100000010011001000111001011110 "
b1100000010011001000111001011110 %
0$
#330
b1100000010111011010110010100111 ;
b1011111100011011111011000010101 :
1$
#335
b110111011010110010100111000000000000000000000000 .
b1001001001010011110110001100000000000000000000000 -
b100011011111011000010101000000000000000000000000 +
0'
b1100000100100100101001111011000 !
b1100000100100100101001111011000 8
b11000001 6
b100100100101001111011000110000000000000000000000 7
b110111011010110010100111 /
b10001101111101100001010100000000000000000000000 ,
b1 2
b100011011111011000010101 0
0(
b11111111 3
b10111111 5
b1100000010111011010110010100111 #
b1100000010111011010110010100111 &
b1011111100011011111011000010101 "
b1011111100011011111011000010101 %
0$
#340
b1011100000011100011101000000111 ;
b11011111001000111011000110110000 :
1$
#345
b101000010111100011000111111001000000000000000000 -
b100011100011101000000111 /
b101000111011000110110000000000000000000000000000 .
b100011100011101000000111000000000000000000000000 +
1'
b10111110 1
b11011111001000010111100011000111 !
b11011111001000010111100011000111 8
b11111111111111111111111111111111 9
b10111110 6
b101000010111100011000111111001000000000000000000 7
b100011100011101000000111000000000000000000 ,
b110 2
b101000111011000110110000 0
b10111000 4
0*
1)
b110 3
b10111110 5
b1011100000011100011101000000111 #
b1011100000011100011101000000111 &
b11011111001000111011000110110000 "
b11011111001000111011000110110000 %
0$
#350
b1100000001010000100101100011111 ;
b11100000011110101101100010001000 :
1$
